hack4u_promixion/__init__.py
hack4u_promixion/cursos.py
hack4u_promixion/utilidades.py
hack4u_promixion-0.1.1.dist-info/METADATA
hack4u_promixion-0.1.1.dist-info/WHEEL
hack4u_promixion-0.1.1.dist-info/top_level.txt
hack4u_promixion-0.1.1.dist-info/RECORD
