Metadata-Version: 2.1
Name: hack4u_promixion
Version: 0.1.1
Summary: Biblioteca para consultar cursos de la academia hack4u.
Home-page: https://hack4u.io/
Author: Promixion
